Metadata-Version: 2.1
Name: rki-scraper
Version: 0.1.8
Summary: Scrape the RKI Data from Arcgis into a Pandas Dataframe
Home-page: UNKNOWN
Author: Grzegorz Lippe
Author-email: grzegorz.lippe@posteo.de
License: UNKNOWN
Platform: UNKNOWN
